[
    {
        "name": "Jeu de 4 tournevis Ingco HKSD0458",
        "price": 110.0,
        "image": "https://bonmarche.mg/wp-content/uploads/2021/11/Jeu-de-4-tournevis-HKSD0458_ingco.jpg",
        "ref": "https://bonmarche.mg/produit/jeu-de-4-tournevis-ingco-hksd0458/",
        "provider": "BonMarché",
        "category_level1": "Informatique",
        "category_level2": "Ordinateur",
        "category_level3": "PC bureau",
        "in_stock": true
    },
    {
        "name": "Jeu de 9 tournevis interchangeables Ingco AKISD0901",
        "price": 240.0,
        "image": "https://bonmarche.mg/wp-content/uploads/2021/11/Jeu-de-9-tournevis-interchangeables-Ingco.jpg",
        "ref": "https://bonmarche.mg/produit/jeu-de-9-tournevis-interchangeables-ingco-akisd0901/",
        "provider": "BonMarché",
        "category_level1": "Informatique",
        "category_level2": "Ordinateur",
        "category_level3": "PC bureau",
        "in_stock": true
    },
    {
        "name": "Set de 6 Tournevis Ingco HKSD0628",
        "price": 210.0,
        "image": "https://bonmarche.mg/wp-content/uploads/2021/11/Set-de-6-Tournevis-hksd0628_ingco.jpg",
        "ref": "https://bonmarche.mg/produit/set-de-6-tournevis-ingco-hksd0628/",
        "provider": "BonMarché",
        "category_level1": "Informatique",
        "category_level2": "Ordinateur",
        "category_level3": "PC bureau",
        "in_stock": true
    },
    {
        "name": "Lot de 32 tournevis de précision Ingco HKSDB0348",
        "price": 320.0,
        "image": "https://bonmarche.mg/wp-content/uploads/2021/11/HKSDB0348_tournevis_ingco.jpg",
        "ref": "https://bonmarche.mg/produit/lot-de-32-tournevis-de-precision-ingco-hksdb0348/",
        "provider": "BonMarché",
        "category_level1": "Informatique",
        "category_level2": "Ordinateur",
        "category_level3": "PC bureau",
        "in_stock": true
    },
    {
        "name": "Laptop 17.3&#8243; Intel Core I7 10510U Asus X712FA-BX839T",
        "price": 0.0,
        "image": "https://bonmarche.mg/wp-content/uploads/2021/07/X712FA-BX839T_asus.jpg",
        "ref": "https://bonmarche.mg/produit/laptop-17-3-intel-core-i7-10510u-asus-x712fa-bx839t/",
        "provider": "BonMarché",
        "category_level1": "Informatique",
        "category_level2": "Ordinateur",
        "category_level3": "PC portable",
        "in_stock": true
    },
    {
        "name": "Laptop N3350 Asus X543NA-C41G1T",
        "price": 17550.0,
        "image": "https://bonmarche.mg/wp-content/uploads/2021/07/X543NA-C41G1T.jpg",
        "ref": "https://bonmarche.mg/produit/laptop-n3350-asus-x543na-c41g1t/",
        "provider": "BonMarché",
        "category_level1": "Informatique",
        "category_level2": "Ordinateur",
        "category_level3": "PC portable",
        "in_stock": true
    },
    {
        "name": "Desktop Asuspro D340MF UC",
        "price": 45500.0,
        "image": "https://bonmarche.mg/wp-content/uploads/2021/07/asuspro_D340MF.jpg",
        "ref": "https://bonmarche.mg/produit/desktop-asuspro-d340mf-uc/",
        "provider": "BonMarché",
        "category_level1": "Informatique",
        "category_level2": "Ordinateur",
        "category_level3": "PC bureau",
        "in_stock": true
    },
    {
        "name": "TOURNEVIS Cr-V 6 PIECES",
        "price": 280.0,
        "image": "https://bonmarche.mg/wp-content/uploads/2020/12/CFH-D01004.jpg",
        "ref": "https://bonmarche.mg/produit/tournevis-cr-v-6-pieces/",
        "provider": "BonMarché",
        "category_level1": "Informatique",
        "category_level2": "Ordinateur",
        "category_level3": "PC bureau",
        "in_stock": true
    },
    {
        "name": "Laptop Intel Core i3-8145U 3,4ghz 17,3” 8go 256Go X712FA-BX379T Asus",
        "price": 29380.0,
        "image": "https://bonmarche.mg/wp-content/uploads/2020/10/X712FA-BX379T.jpg",
        "ref": "https://bonmarche.mg/produit/laptop-intel-core-i3-8145u-34ghz-173-8go-256go-x712fa-bx379t-asus/",
        "provider": "BonMarché",
        "category_level1": "Informatique",
        "category_level2": "Ordinateur",
        "category_level3": "PC portable",
        "in_stock": true
    },
    {
        "name": "Laptop Intel Celeron Dual 2,6ghz E406MA-BV005T Asus",
        "price": 14950.0,
        "image": "https://bonmarche.mg/wp-content/uploads/2020/10/E406MA-BV005T.jpg",
        "ref": "https://bonmarche.mg/produit/laptop-intel-celeron-dual-26ghz-e406ma-bv005t-asus/",
        "provider": "BonMarché",
        "category_level1": "Informatique",
        "category_level2": "Ordinateur",
        "category_level3": "PC portable",
        "in_stock": true
    },
    {
        "name": "Laptop Intel Celeron 2,2ghz N4000-E203MA-FD014 Asus",
        "price": 13980.0,
        "image": "https://bonmarche.mg/wp-content/uploads/2020/10/N4000-E203MA-FD014.jpg",
        "ref": "https://bonmarche.mg/produit/laptop-intel-celeron-22ghz-n4000-e203ma-fd014-asus/",
        "provider": "BonMarché",
        "category_level1": "Informatique",
        "category_level2": "Ordinateur",
        "category_level3": "PC portable",
        "in_stock": true
    },
    {
        "name": "Laptop Core i3 8130U 2,2GHz X543UA-DM 2351 Asus",
        "price": 28600.0,
        "image": "https://bonmarche.mg/wp-content/uploads/2020/10/X543UA-DM-2351.jpg",
        "ref": "https://bonmarche.mg/produit/laptop-core-i3-8130u-22ghz-x543ua-dm-2351-asus/",
        "provider": "BonMarché",
        "category_level1": "Informatique",
        "category_level2": "Ordinateur",
        "category_level3": "PC portable",
        "in_stock": true
    },
    {
        "name": "Revitalift CicaCrème Soin Contour des Yeux 15ml L&#8217;Oréal",
        "price": 642.0,
        "image": "https://bonmarche.mg/wp-content/uploads/2020/09/REVITALIFT-CICACREM-EYE.jpg",
        "ref": "https://bonmarche.mg/produit/revitalift-cicacreme-soin-contour-des-yeux-15ml-loreal/",
        "provider": "BonMarché",
        "category_level1": "Informatique",
        "category_level2": "Ordinateur",
        "category_level3": "PC bureau",
        "in_stock": true
    },
    {
        "name": "GPD pocket mini-ordinateur portable (syst Windows 10)",
        "price": 20870.0,
        "image": "https://bonmarche.mg/wp-content/uploads/2020/09/5486_P_1502670011234.jpg",
        "ref": "https://bonmarche.mg/produit/gpd-pocket-mini-ordinateur-portable-syst-windows-10/",
        "provider": "BonMarché",
        "category_level1": "Informatique",
        "category_level2": "Ordinateur",
        "category_level3": "PC portable",
        "in_stock": true
    },
    {
        "name": "Jumper EZbook 2 Ultrabook 14.1 Pouce",
        "price": 10390.0,
        "image": "https://bonmarche.mg/wp-content/uploads/2020/09/5487_P_1502671005211.jpg",
        "ref": "https://bonmarche.mg/produit/jumper-ezbook-2-ultrabook-14-1-pouce/",
        "provider": "BonMarché",
        "category_level1": "Informatique",
        "category_level2": "Ordinateur",
        "category_level3": "Ordinateur",
        "in_stock": true
    }
]